jsarray/__init__.py
js_array-0.0.1.dist-info/METADATA
js_array-0.0.1.dist-info/WHEEL
js_array-0.0.1.dist-info/top_level.txt
js_array-0.0.1.dist-info/RECORD
